Metadata-Version: 2.1
Name: interpcl
Version: 2021.3.11
Summary: interpolate angular power spectra
Home-page: https://github.com/ntessore/interpcl
Maintainer: Nicolas Tessore
Maintainer-email: n.tessore@ucl.ac.uk
License: MIT
Project-URL: Documentation, https://cltools.readthedocs.io/interpcl/
Platform: UNKNOWN
Classifier: Programming Language :: Python :: 3
Classifier: License :: OSI Approved :: MIT License
Classifier: Operating System :: OS Independent
Requires-Python: >=3.6
